Workbook

Sheet Dashboard
A1: DASHBOARD MARKETING
A3: Ringkasan performa full funnel — terhubung otomatis ke Campaign Meta Ads
A5: TOTAL BUDGET (RP) | D5: IMPRESSION | G5: REACH | J5: KLIK LINK
A6: =SUM('Campaign Meta Ads'!F2:F51) -> 4500000 | D6: =SUM('Campaign Meta Ads'!G2:G51) -> 340000 | G6: =SUM('Campaign Meta Ads'!H2:H51) -> 235000 | J6: =SUM('Campaign Meta Ads'!J2:J51) -> 7300
A10: LEADS | D10: CLOSING | G10: OMZET (RP)
A11: =SUM('Campaign Meta Ads'!Q2:Q51) -> 355 | D11: =SUM('Campaign Meta Ads'!S2:S51) -> 117 | G11: =SUM('Campaign Meta Ads'!U2:U51) -> 72500000
A15: KPI | B15: Target | C15: Realisasi | D15: Pencapaian | F15: Campaign | G15: Budget | H15: Omzet
A16: Reach | B16: ='Target KPI'!B5 -> 500000 | C16: =SUM('Campaign Meta Ads'!H2:H51) -> 235000 | D16: =IF(B16=0,"",C16/B16) -> 0.47 | F16: =IF('Campaign Meta Ads'!C2="","",'Campaign Meta Ads'!C2) -> Kelas SR+AR | G16: =IF('Campaign Meta Ads'!C2="","",'Campaign Meta Ads'!F2) -> 3000000 | H16: =IF('Campaign Meta Ads'!C2="","",'Campaign Meta Ads'!U2) -> 42500000
A17: Klik Link | B17: ='Target KPI'!B6 -> 3000 | C17: =SUM('Campaign Meta Ads'!J2:J51) -> 7300 | D17: =IF(B17=0,"",C17/B17) -> 2.4333333 | F17: =IF('Campaign Meta Ads'!C3="","",'Campaign Meta Ads'!C3) -> Kelas AR | G17: =IF('Campaign Meta Ads'!C3="","",'Campaign Meta Ads'!F3) -> 1500000 | H17: =IF('Campaign Meta Ads'!C3="","",'Campaign Meta Ads'!U3) -> 30000000
A18: Leads | B18: ='Target KPI'!B7 -> 500 | C18: =SUM('Campaign Meta Ads'!Q2:Q51) -> 355 | D18: =IF(B18=0,"",C18/B18) -> 0.71 | F18: =IF('Campaign Meta Ads'!C4="","",'Campaign Meta Ads'!C4) | G18: =IF('Campaign Meta Ads'!C4="","",'Campaign Meta Ads'!F4) | H18: =IF('Campaign Meta Ads'!C4="","",'Campaign Meta Ads'!U4)
A19: Closing | B19: ='Target KPI'!B8 -> 433 | C19: =SUM('Campaign Meta Ads'!S2:S51) -> 117 | D19: =IF(B19=0,"",C19/B19) -> 0.27020785 | F19: =IF('Campaign Meta Ads'!C5="","",'Campaign Meta Ads'!C5) | G19: =IF('Campaign Meta Ads'!C5="","",'Campaign Meta Ads'!F5) | H19: =IF('Campaign Meta Ads'!C5="","",'Campaign Meta Ads'!U5)
A20: Omzet (Rp) | B20: ='Target KPI'!B9 -> 6500000000 | C20: =SUM('Campaign Meta Ads'!U2:U51) -> 72500000 | D20: =IF(B20=0,"",C20/B20) -> 0.011153846 | F20: =IF('Campaign Meta Ads'!C6="","",'Campaign Meta Ads'!C6) | G20: =IF('Campaign Meta Ads'!C6="","",'Campaign Meta Ads'!F6) | H20: =IF('Campaign Meta Ads'!C6="","",'Campaign Meta Ads'!U6)
F21: =IF('Campaign Meta Ads'!C7="","",'Campaign Meta Ads'!C7) | G21: =IF('Campaign Meta Ads'!C7="","",'Campaign Meta Ads'!F7) | H21: =IF('Campaign Meta Ads'!C7="","",'Campaign Meta Ads'!U7)
F22: =IF('Campaign Meta Ads'!C8="","",'Campaign Meta Ads'!C8) | G22: =IF('Campaign Meta Ads'!C8="","",'Campaign Meta Ads'!F8) | H22: =IF('Campaign Meta Ads'!C8="","",'Campaign Meta Ads'!U8)
F23: =IF('Campaign Meta Ads'!C9="","",'Campaign Meta Ads'!C9) | G23: =IF('Campaign Meta Ads'!C9="","",'Campaign Meta Ads'!F9) | H23: =IF('Campaign Meta Ads'!C9="","",'Campaign Meta Ads'!U9)
F24: =IF('Campaign Meta Ads'!C10="","",'Campaign Meta Ads'!C10) | G24: =IF('Campaign Meta Ads'!C10="","",'Campaign Meta Ads'!F10) | H24: =IF('Campaign Meta Ads'!C10="","",'Campaign Meta Ads'!U10)
F25: =IF('Campaign Meta Ads'!C11="","",'Campaign Meta Ads'!C11) | G25: =IF('Campaign Meta Ads'!C11="","",'Campaign Meta Ads'!F11) | H25: =IF('Campaign Meta Ads'!C11="","",'Campaign Meta Ads'!U11)

Sheet Data Harian
A1: Tanggal | B1: Campaign | C1: Platform | D1: Reach | E1: Klik | F1: Share | G1: Save | H1: Profil | I1: Followers | J1: Chat | K1: Biaya | L1: Leads | M1: Closing

Sheet Target KPI
A1: TARGET KPI MARKETING
A2: Target operasional untuk perbandingan pada Dashboard
A4: Indikator | B4: Target | C4: Satuan
A5: Reach | B5: 500000 | C5: akun
A6: Klik Link | B6: 3000 | C6: klik
A7: Leads | B7: 500 | C7: lead
A8: Closing | B8: 433 | C8: closing
A9: Omzet | B9: 6500000000 | C9: rupiah

Sheet Performa Konten
A1: Tanggal | B1: Konten | C1: Jenis | D1: Reach | E1: Klik | F1: Share | G1: Save | H1: Leads | I1: Closing

Sheet Campaign Meta Ads
A1: Tanggal | B1: Bulan | C1: Campaign | D1: Objective | E1: Platform | F1: Budget | G1: Impression | H1: Reach | I1: Frequency | J1: Klik Link | K1: CTR | L1: CPC | M1: CPM | N1: Kunjungan Profil | O1: Chat | P1: Cost per Chat | Q1: Leads | R1: CPL | S1: Closing | T1: Closing Rate | U1: Omzet | V1: ROAS | W1: ROI | X1: Status | Y1: Catatan
A2: 46235 | B2: =IF(A2="","",TEXT(A2,"mmmm")) -> Agustus | C2: Kelas SR+AR | D2: Leads | E2: Instagram | F2: 3000000 | G2: 220000 | H2: 150000 | I2: =IF(H2=0,"",G2/H2) -> 1.4666667 | J2: 4500 | K2: =IF(G2=0,"",J2/G2) -> 0.020454545 | L2: =IF(J2=0,"",F2/J2) -> 666.66667 | M2: =IF(G2=0,"",(F2/G2)*1000) -> 13636.364 | N2: 1200 | O2: 520 | P2: =IF(O2=0,"",F2/O2) -> 5769.2308 | Q2: 210 | R2: =IF(Q2=0,"",F2/Q2) -> 14285.714 | S2: 68 | T2: =IF(Q2=0,"",S2/Q2) -> 0.32380952 | U2: 42500000 | V2: =IF(F2=0,"",U2/F2) -> 14.166667 | W2: =IF(F2=0,"",(U2-F2)/F2) -> 13.166667 | X2: Aktif | Y2: Contoh kampanye akuisisi utama
A3: 46236 | B3: =IF(A3="","",TEXT(A3,"mmmm")) -> Agustus | C3: Kelas AR | D3: Leads | E3: Facebook | F3: 1500000 | G3: 120000 | H3: 85000 | I3: =IF(H3=0,"",G3/H3) -> 1.4117647 | J3: 2800 | K3: =IF(G3=0,"",J3/G3) -> 0.023333333 | L3: =IF(J3=0,"",F3/J3) -> 535.71429 | M3: =IF(G3=0,"",(F3/G3)*1000) -> 12500 | N3: 850 | O3: 340 | P3: =IF(O3=0,"",F3/O3) -> 4411.7647 | Q3: 145 | R3: =IF(Q3=0,"",F3/Q3) -> 10344.828 | S3: 49 | T3: =IF(Q3=0,"",S3/Q3) -> 0.33793103 | U3: 30000000 | V3: =IF(F3=0,"",U3/F3) -> 20 | W3: =IF(F3=0,"",(U3-F3)/F3) -> 19 | X3: Selesai | Y3: Contoh kampanye trial class
B4: =IF(A4="","",TEXT(A4,"mmmm")) | I4: =IF(H4=0,"",G4/H4) | K4: =IF(G4=0,"",J4/G4) | L4: =IF(J4=0,"",F4/J4) | M4: =IF(G4=0,"",(F4/G4)*1000) | P4: =IF(O4=0,"",F4/O4) | R4: =IF(Q4=0,"",F4/Q4) | T4: =IF(Q4=0,"",S4/Q4) | V4: =IF(F4=0,"",U4/F4) | W4: =IF(F4=0,"",(U4-F4)/F4)
B5: =IF(A5="","",TEXT(A5,"mmmm")) | I5: =IF(H5=0,"",G5/H5) | K5: =IF(G5=0,"",J5/G5) | L5: =IF(J5=0,"",F5/J5) | M5: =IF(G5=0,"",(F5/G5)*1000) | P5: =IF(O5=0,"",F5/O5) | R5: =IF(Q5=0,"",F5/Q5) | T5: =IF(Q5=0,"",S5/Q5) | V5: =IF(F5=0,"",U5/F5) | W5: =IF(F5=0,"",(U5-F5)/F5)
B6: =IF(A6="","",TEXT(A6,"mmmm")) | I6: =IF(H6=0,"",G6/H6) | K6: =IF(G6=0,"",J6/G6) | L6: =IF(J6=0,"",F6/J6) | M6: =IF(G6=0,"",(F6/G6)*1000) | P6: =IF(O6=0,"",F6/O6) | R6: =IF(Q6=0,"",F6/Q6) | T6: =IF(Q6=0,"",S6/Q6) | V6: =IF(F6=0,"",U6/F6) | W6: =IF(F6=0,"",(U6-F6)/F6)
B7: =IF(A7="","",TEXT(A7,"mmmm")) | I7: =IF(H7=0,"",G7/H7) | K7: =IF(G7=0,"",J7/G7) | L7: =IF(J7=0,"",F7/J7) | M7: =IF(G7=0,"",(F7/G7)*1000) | P7: =IF(O7=0,"",F7/O7) | R7: =IF(Q7=0,"",F7/Q7) | T7: =IF(Q7=0,"",S7/Q7) | V7: =IF(F7=0,"",U7/F7) | W7: =IF(F7=0,"",(U7-F7)/F7)
B8: =IF(A8="","",TEXT(A8,"mmmm")) | I8: =IF(H8=0,"",G8/H8) | K8: =IF(G8=0,"",J8/G8) | L8: =IF(J8=0,"",F8/J8) | M8: =IF(G8=0,"",(F8/G8)*1000) | P8: =IF(O8=0,"",F8/O8) | R8: =IF(Q8=0,"",F8/Q8) | T8: =IF(Q8=0,"",S8/Q8) | V8: =IF(F8=0,"",U8/F8) | W8: =IF(F8=0,"",(U8-F8)/F8)
B9: =IF(A9="","",TEXT(A9,"mmmm")) | I9: =IF(H9=0,"",G9/H9) | K9: =IF(G9=0,"",J9/G9) | L9: =IF(J9=0,"",F9/J9) | M9: =IF(G9=0,"",(F9/G9)*1000) | P9: =IF(O9=0,"",F9/O9) | R9: =IF(Q9=0,"",F9/Q9) | T9: =IF(Q9=0,"",S9/Q9) | V9: =IF(F9=0,"",U9/F9) | W9: =IF(F9=0,"",(U9-F9)/F9)
B10: =IF(A10="","",TEXT(A10,"mmmm")) | I10: =IF(H10=0,"",G10/H10) | K10: =IF(G10=0,"",J10/G10) | L10: =IF(J10=0,"",F10/J10) | M10: =IF(G10=0,"",(F10/G10)*1000) | P10: =IF(O10=0,"",F10/O10) | R10: =IF(Q10=0,"",F10/Q10) | T10: =IF(Q10=0,"",S10/Q10) | V10: =IF(F10=0,"",U10/F10) | W10: =IF(F10=0,"",(U10-F10)/F10)
B11: =IF(A11="","",TEXT(A11,"mmmm")) | I11: =IF(H11=0,"",G11/H11) | K11: =IF(G11=0,"",J11/G11) | L11: =IF(J11=0,"",F11/J11) | M11: =IF(G11=0,"",(F11/G11)*1000) | P11: =IF(O11=0,"",F11/O11) | R11: =IF(Q11=0,"",F11/Q11) | T11: =IF(Q11=0,"",S11/Q11) | V11: =IF(F11=0,"",U11/F11) | W11: =IF(F11=0,"",(U11-F11)/F11)
B12: =IF(A12="","",TEXT(A12,"mmmm")) | I12: =IF(H12=0,"",G12/H12) | K12: =IF(G12=0,"",J12/G12) | L12: =IF(J12=0,"",F12/J12) | M12: =IF(G12=0,"",(F12/G12)*1000) | P12: =IF(O12=0,"",F12/O12) | R12: =IF(Q12=0,"",F12/Q12) | T12: =IF(Q12=0,"",S12/Q12) | V12: =IF(F12=0,"",U12/F12) | W12: =IF(F12=0,"",(U12-F12)/F12)
B13: =IF(A13="","",TEXT(A13,"mmmm")) | I13: =IF(H13=0,"",G13/H13) | K13: =IF(G13=0,"",J13/G13) | L13: =IF(J13=0,"",F13/J13) | M13: =IF(G13=0,"",(F13/G13)*1000) | P13: =IF(O13=0,"",F13/O13) | R13: =IF(Q13=0,"",F13/Q13) | T13: =IF(Q13=0,"",S13/Q13) | V13: =IF(F13=0,"",U13/F13) | W13: =IF(F13=0,"",(U13-F13)/F13)
B14: =IF(A14="","",TEXT(A14,"mmmm")) | I14: =IF(H14=0,"",G14/H14) | K14: =IF(G14=0,"",J14/G14) | L14: =IF(J14=0,"",F14/J14) | M14: =IF(G14=0,"",(F14/G14)*1000) | P14: =IF(O14=0,"",F14/O14) | R14: =IF(Q14=0,"",F14/Q14) | T14: =IF(Q14=0,"",S14/Q14) | V14: =IF(F14=0,"",U14/F14) | W14: =IF(F14=0,"",(U14-F14)/F14)
B15: =IF(A15="","",TEXT(A15,"mmmm")) | I15: =IF(H15=0,"",G15/H15) | K15: =IF(G15=0,"",J15/G15) | L15: =IF(J15=0,"",F15/J15) | M15: =IF(G15=0,"",(F15/G15)*1000) | P15: =IF(O15=0,"",F15/O15) | R15: =IF(Q15=0,"",F15/Q15) | T15: =IF(Q15=0,"",S15/Q15) | V15: =IF(F15=0,"",U15/F15) | W15: =IF(F15=0,"",(U15-F15)/F15)
... B51: =IF(A51="","",TEXT(A51,"mmmm")) | I51: =IF(H51=0,"",G51/H51) | K51: =IF(G51=0,"",J51/G51) | L51: =IF(J51=0,"",F51/J51) | M51: =IF(G51=0,"",(F51/G51)*1000) | P51: =IF(O51=0,"",F51/O51) | R51: =IF(Q51=0,"",F51/Q51) | T51: =IF(Q51=0,"",S51/Q51) | V51: =IF(F51=0,"",U51/F51) | W51: =IF(F51=0,"",(U51-F51)/F51)

Sheet Database Leads
A1: Nama | B1: Kota | C1: Program | D1: Sumber | E1: Status | F1: PIC | G1: Follow Up | H1: Closing

Sheet Data Closing
A1: Tanggal | B1: Lead | C1: Nilai | D1: Status

Sheet Performa Marketing
A1: PIC | B1: Leads | C1: Follow Up | D1: Closing | E1: Conversion

Sheet Referensi
A1: REFERENSI & KAMUS KPI
A3: Daftar pilihan input dan definisi metrik yang digunakan dalam workbook
A5: Platform | B5: Objective | C5: Status Campaign | D5: Status Lead | E5: PIC | G5: KPI | H5: Rumus | I5: Makna | J5: Format
A6: Facebook | B6: Awareness | C6: Aktif | D6: Baru | E6: Marketing 1 | G6: Frequency | H6: Impression / Reach | I6: Rata-rata frekuensi tayang | J6: 0.00x
A7: Instagram | B7: Traffic | C7: Selesai | D7: Follow Up | E7: Marketing 2 | G7: CTR | H7: Klik Link / Impression | I7: Efektivitas iklan menghasilkan klik | J7: %
A8: TikTok | B8: Engagement | C8: Pause | D8: Qualified | E8: Marketing 3 | G8: CPC | H8: Budget / Klik Link | I8: Biaya per klik | J8: Rp
A9: Google | B9: Leads | D9: Closing | G9: CPM | H9: Budget / Impression × 1.000 | I9: Biaya per seribu tayangan | J9: Rp
B10: Sales | D10: Tidak Closing | G10: Cost per Chat | H10: Budget / Chat | I10: Biaya per percakapan | J10: Rp
G11: CPL | H11: Budget / Leads | I11: Biaya per lead | J11: Rp
G12: Closing Rate | H12: Closing / Leads | I12: Persentase lead menjadi closing | J12: %
G13: ROAS | H13: Omzet / Budget | I13: Pendapatan per biaya iklan | J13: x
G14: ROI | H14: (Omzet − Budget) / Budget | I14: Imbal hasil setelah biaya iklan | J14: %
G15: Pencapaian | H15: Realisasi / Target | I15: Realisasi dibanding target | J15: %

Sheet Dashboard Funnel
A1: DASHBOARD FUNNEL
A3: Pergerakan audiens dari awareness hingga revenue
A5: Tahapan | B5: Jumlah | C5: Konversi dari tahap sebelumnya
A6: Impression | B6: =SUM('Campaign Meta Ads'!G2:G51) -> 340000 | C6: 1
A7: Reach | B7: =SUM('Campaign Meta Ads'!H2:H51) -> 235000 | C7: =IF(B6=0,"",B7/B6) -> 0.69117647
A8: Klik Link | B8: =SUM('Campaign Meta Ads'!J2:J51) -> 7300 | C8: =IF(B7=0,"",B8/B7) -> 0.03106383
A9: Kunjungan Profil | B9: =SUM('Campaign Meta Ads'!N2:N51) -> 2050 | C9: =IF(B8=0,"",B9/B8) -> 0.28082192
A10: Chat | B10: =SUM('Campaign Meta Ads'!O2:O51) -> 860 | C10: =IF(B9=0,"",B10/B9) -> 0.4195122
A11: Leads | B11: =SUM('Campaign Meta Ads'!Q2:Q51) -> 355 | C11: =IF(B10=0,"",B11/B10) -> 0.4127907
A12: Closing | B12: =SUM('Campaign Meta Ads'!S2:S51) -> 117 | C12: =IF(B11=0,"",B12/B11) -> 0.32957746
A13: Omzet | B13: =SUM('Campaign Meta Ads'!U2:U51) -> 72500000 | C13: —
